pk_ai_tools/__init__.py
pk_ai_tools/document_ingestor.py
pk_ai_tools/rag_pipeline.py
pk_ai_tools-0.2.0.dist-info/METADATA
pk_ai_tools-0.2.0.dist-info/WHEEL
pk_ai_tools-0.2.0.dist-info/licenses/LICENSE
pk_ai_tools-0.2.0.dist-info/RECORD
